random_words_generator/__init__.py
random_words_generator/words.py
random_words_genrator/__init__.py
random_words_genrator/words.py
test/__init__.py
test/test_words.py
random_words_generator_fr-0.3.dist-info/LICENSE
random_words_generator_fr-0.3.dist-info/METADATA
random_words_generator_fr-0.3.dist-info/WHEEL
random_words_generator_fr-0.3.dist-info/top_level.txt
random_words_generator_fr-0.3.dist-info/RECORD
