Metadata-Version: 2.1
Name: random_words_generator_fr
Version: 0.3
Summary: Génère un nombre spécifié de mots français au hasard, entre 0 et 20 mots. Par défaut, génère 8 mots. utile pour divers projets nécessitant des mots français aléatoires. Permet de générer des mots pour des jeux, des tests de vocabulaire, des noms de fichiers uniques, et bien plus encore.
Author: killymeed
Author-email: gowleytizie@proton.me
Keywords: mots français aléatoires générateur de mots
Classifier: Development Status :: 3 - Alpha
Classifier: Intended Audience :: Developers
Classifier: License :: OSI Approved :: MIT License
Classifier: Programming Language :: Python :: 3
Classifier: Programming Language :: Python :: 3.6
Classifier: Programming Language :: Python :: 3.7
Classifier: Programming Language :: Python :: 3.8
Classifier: Programming Language :: Python :: 3.9
Classifier: Programming Language :: Python :: 3.10
Classifier: Programming Language :: Python :: 3.11
Classifier: Programming Language :: Python :: 3.12
Requires-Python: >=3.6
License-File: LICENSE
Provides-Extra: dev
